{
    "name": "Indebted Spirit",
    "type_line": "Enchantment Creature — Spirit",
    "mana_cost": "{W}",
    "cmc": 1.0,
    "oracle_text": "Bestow {2}{W} (If you cast this card for its bestow cost, it's an Aura spell with enchant creature. It becomes a creature again if it's not attached.)\nAfterlife 1 (When this permanent is put into a graveyard from the battlefield, create a 1/1 white and black Spirit creature token with flying.)\nEnchanted creature gets +1/+1 and has afterlife 1.",
    "power": "1",
    "toughness": "1",
    "rarity": "uncommon",
    "colors": [
        "W"
    ],
    "image_url": "assets\\cards\\Criaturas\\indebted_spirit.jpg",
    "quantity": 1
}